[
  {
    "id": 1735063337445,
    "name": "רון",
    "class": "י\"ב 2",
    "phone": " 050-1234567"
  },
  {
    "id": 1735063343341,
    "name": "דן",
    "class": "י\"א 4",
    "phone": "053-5317356"
  },
  {
    "id": 1735063358132,
    "name": "דניאל",
    "class": "ח' 1",
    "phone": "050-1234333"
  },
  {
    "id": 1735493599675,
    "name": "שני",
    "class": "ט' 4",
    "phone": "050-7564666"
  },
  {
    "id": 1735573351385,
    "name": "תמר",
    "class": "י' 1",
    "phone": "053-7654321"
  },
  {
    "id": 1735583650919,
    "name": "רוני",
    "class": "ז' 1",
    "phone": "054-0835648"
  }
]
